dpq/__init__.py
dpq/dpq.py
dpq/prompts/classify_sentiment.json
dpq/prompts/translate_to_english.json
dpq-0.1.5.dist-info/LICENSE
dpq-0.1.5.dist-info/METADATA
dpq-0.1.5.dist-info/WHEEL
dpq-0.1.5.dist-info/RECORD
