Metadata-Version: 2.1
Name: dpq
Version: 0.1.5
Summary: dpq is an open-source python library that makes prompt-based data processing and feature engineering easy.
License: Apache-2.0
Author: dpq
Author-email: dpq.code@gmail.com
Requires-Python: >=3.8.1,<3.13
Classifier: License :: OSI Approved :: Apache Software License
Classifier: Programming Language :: Python :: 3
Classifier: Programming Language :: Python :: 3.9
Classifier: Programming Language :: Python :: 3.10
Classifier: Programming Language :: Python :: 3.11
Classifier: Programming Language :: Python :: 3.12
Requires-Dist: requests (>=2.31.0,<3.0.0)
Requires-Dist: tqdm (>=4.66.2,<5.0.0)
